grepshift/__init__.py
grepshift/__main__.py
grepshift-1.5.1.dist-info/METADATA
grepshift-1.5.1.dist-info/WHEEL
grepshift-1.5.1.dist-info/entry_points.txt
grepshift-1.5.1.dist-info/licenses/LICENSE
grepshift-1.5.1.dist-info/RECORD
