Metadata-Version: 2.4
Name: grepshift
Version: 1.5.1
Summary: Find and replace all instances of a string with a new string in a directory and all its sub-directories.
License-Expression: MIT
License-File: LICENSE
Keywords: find,replace,string,text,batch,bulk,utility,command-line,cli
Author: Steve Scholnick
Author-email: scholnicks@gmail.com
Requires-Python: >=3.13
Classifier: Development Status :: 5 - Production/Stable
Classifier: Intended Audience :: Developers
Classifier: Programming Language :: Python :: 3.13
Classifier: Programming Language :: Python :: 3.14
Classifier: License :: OSI Approved :: MIT License
Classifier: Topic :: Utilities
Requires-Dist: docopt-ng (>=0.9.0,<0.10.0)
Project-URL: Homepage, https://pypi.org/project/grepshift/
Project-URL: Issues, https://github.com/scholnicks/grepshift/issues
Project-URL: Repository, https://github.com/scholnicks/grepshift/
